timeseries_fastai/__init__.py
timeseries_fastai/_nbdev.py
timeseries_fastai/core.py
timeseries_fastai/data.py
timeseries_fastai/imports.py
timeseries_fastai/models.py
timeseries_fastai/tabular.py
timeseries_fastai-2.1.1.dist-info/LICENSE
timeseries_fastai-2.1.1.dist-info/METADATA
timeseries_fastai-2.1.1.dist-info/WHEEL
timeseries_fastai-2.1.1.dist-info/entry_points.txt
timeseries_fastai-2.1.1.dist-info/top_level.txt
timeseries_fastai-2.1.1.dist-info/RECORD
