Metadata-Version: 2.1
Name: timeseries-fastai
Version: 2.1.1
Summary: A timeseries lib on top of fastai
Home-page: https://github.com/tcapelle/timeseries_fastai
Author: Thomas Capelle
Author-email: tcapelle@protonmail.com
License: Apache Software License 2.0
Keywords: timeseries deeplearning fastai
Platform: UNKNOWN
Classifier: Development Status :: 3 - Alpha
Classifier: Intended Audience :: Developers
Classifier: License :: OSI Approved :: Apache Software License
Classifier: Natural Language :: English
Classifier: Programming Language :: Python :: 3.6
Classifier: Programming Language :: Python :: 3.7
Classifier: Programming Language :: Python :: 3.8
Requires-Python: >=3.6
Requires-Dist: fastai
Requires-Dist: fastcore
Requires-Dist: nbdev
